bin/DFx/inv.v
module inv(
  in,
  out   );
    output reg out;
    input wire in ;

  always @(*)
begin
  out = ~in ;
  end

endmodule

bin/DFx/dfx.v
module FF_scan(
  clk,
  SE,
  SD,
  D,
  Q
  );
    output reg  Q;
    input wire D;
    input wire SE;
    input wire clk;
    input wire SD;

  always @(posedge clk)
    begin
   if (SE== 0 ) Q =  D else Q = SD;
    end

endmodule

bin/DFx/dfx8bit.v
module FF_scan8(
  rclk,
  rSE,
  rSD,
  rD,
  Q8
  );
    wire [7:0] wQ ;
	wire [7:0] OutInv ;
	output reg Q8;
    input wire rD;
    input wire rSE;
    input wire rclk;
    input wire rSD;

always @(posedge rclk) begin
	 Q8 = wQ[7] ;
end
  FF_scan FF_scan_intance0(
  .clk(rclk),
  .SE(rSE),
  .SD(rSD),
  .D(rD),
  .Q(wQ[0])
  );

inv intance0(
  .in (wQ[0]),
  .out (OutInv[0]
    )
  );



 FF_scan FF_scan_intance1(
  .clk(rclk),
  .SE(rSE),
  .SD(wQ[0]),
  .D(OutInv[0]),
  .Q(wQ[1])
  );


inv intance1(
  .in(wQ[1]),
  .out(OutInv[1]  )
  );

 FF_scan FF_scan_intance2(
  .clk(rclk),
  .SE(rSE),
  .SD(wQ[1]),
  .D(OutInv[1]),
  .Q(wQ[2])
  );


inv intance2(
  .in(wQ[2]),
  .out(OutInv[2] )
   );


 FF_scan FF_scan_intance3(
  .clk(rclk),
  .SE(rSE),
  .SD(wQ[2]),
  .D(OutInv[2]),
  .Q(wQ[3])
  ); 


inv intance3(
  .in(wQ[3]),
  .out(OutInv[3] )
  );

 FF_scan FF_scan_intance4(
  .clk(rclk),
  .SE(rSE),
  .SD(wQ[3]),
  .D(OutInv[3]),
  .Q(wQ[4])
  );

inv intance4(
  .in(wQ[4]),
  .out(OutInv[4])
  );


 FF_scan FF_scan_intance5(
  .clk(rclk),
  .SE(rSE),
  .SD(wQ[4]),
  .D(OutInv[4]),
  .Q(wQ[5])
  );


inv intance5(
  .in(wQ[5]),
  .out(OutInv[5])
  );


 FF_scan FF_scan_intance6(
  .clk(rclk),
  .SE(rSE),
  .SD(wQ[5]),
  .D(OutInv[5]),
  .Q(wQ[6])
  );


inv intance6(
  .in(wQ[6]),
  .out(OutInv[6])
  );


 FF_scan FF_scan_intance7(
  .clk(rclk),
  .SE(rSE),
  .SD(wQ[6]),
  .D(OutInv[6]),
  .Q(wQ[7])
  );

 inv intance7(
  .in(wQ[7]),
  .out(OutInv[7])
  );
endmodule

bin/DFx/TBdfx.v
module tester;
reg TBSE ;
reg TBSD ;
reg TBD;
wire wQout;

reg TBclk = 1;
always #1 TBclk =! TBclk;

  initial begin
     $dumpfile("tester.vcd");
     $dumpvars(0,tester);
     TBSE = 0;
     TBSD = 1;
     TBD = 0;
 
     # 20 TBSE= 1;
       TBSD= 0;
       TBD= 1;
      # 20
       TBSE= 0;
       # 2
         TBSE= 1;
     # 513 $finish;
  end

FF_scan8 FF_scan8_intance0(
  .rclk(TBclk),
  .rSE(TBSE),
  .rSD(TBSD),
  .rD(TBD),
  .Q8 (wQout)
  );
endmodule

bin/DFx/tester.vcd
$date
	Sun Oct  7 15:22:48 2018
$end
$version
	Icarus Verilog
$end
$timescale
	1s
$end
$scope module tester $end
$var wire 1 ! wQout $end
$var reg 1 " TBD $end
$var reg 1 # TBSD $end
$var reg 1 $ TBSE $end
$var reg 1 % TBclk $end
$scope module FF_scan8_intance0 $end
$var wire 1 " rD $end
$var wire 1 # rSD $end
$var wire 1 $ rSE $end
$var wire 1 % rclk $end
$var wire 8 & wQ [7:0] $end
$var wire 8 ' OutInv [7:0] $end
$var reg 1 ! Q8 $end
$scope module FF_scan_intance0 $end
$var wire 1 " D $end
$var wire 1 # SD $end
$var wire 1 $ SE $end
$var wire 1 % clk $end
$var reg 1 ( Q $end
$upscope $end
$scope module FF_scan_intance1 $end
$var wire 1 ) D $end
$var wire 1 * SD $end
$var wire 1 $ SE $end
$var wire 1 % clk $end
$var reg 1 + Q $end
$upscope $end
$scope module FF_scan_intance2 $end
$var wire 1 , D $end
$var wire 1 - SD $end
$var wire 1 $ SE $end
$var wire 1 % clk $end
$var reg 1 . Q $end
$upscope $end
$scope module FF_scan_intance3 $end
$var wire 1 / D $end
$var wire 1 0 SD $end
$var wire 1 $ SE $end
$var wire 1 % clk $end
$var reg 1 1 Q $end
$upscope $end
$scope module FF_scan_intance4 $end
$var wire 1 2 D $end
$var wire 1 3 SD $end
$var wire 1 $ SE $end
$var wire 1 % clk $end
$var reg 1 4 Q $end
$upscope $end
$scope module FF_scan_intance5 $end
$var wire 1 5 D $end
$var wire 1 6 SD $end
$var wire 1 $ SE $end
$var wire 1 % clk $end
$var reg 1 7 Q $end
$upscope $end
$scope module FF_scan_intance6 $end
$var wire 1 8 D $end
$var wire 1 9 SD $end
$var wire 1 $ SE $end
$var wire 1 % clk $end
$var reg 1 : Q $end
$upscope $end
$scope module FF_scan_intance7 $end
$var wire 1 ; D $end
$var wire 1 < SD $end
$var wire 1 $ SE $end
$var wire 1 % clk $end
$var reg 1 = Q $end
$upscope $end
$scope module intance0 $end
$var wire 1 > in $end
$var reg 1 ? out $end
$upscope $end
$scope module intance1 $end
$var wire 1 @ in $end
$var reg 1 A out $end
$upscope $end
$scope module intance2 $end
$var wire 1 B in $end
$var reg 1 C out $end
$upscope $end
$scope module intance3 $end
$var wire 1 D in $end
$var reg 1 E out $end
$upscope $end
$scope module intance4 $end
$var wire 1 F in $end
$var reg 1 G out $end
$upscope $end
$scope module intance5 $end
$var wire 1 H in $end
$var reg 1 I out $end
$upscope $end
$scope module intance6 $end
$var wire 1 J in $end
$var reg 1 K out $end
$upscope $end
$scope module intance7 $end
$var wire 1 L in $end
$var reg 1 M out $end
$upscope $end
$upscope $end
$upscope $end
$enddefinitions $end
#0
$dumpvars
xM
xL
xK
xJ
xI
xH
xG
xF
xE
xD
xC
xB
xA
x@
1?
0>
x=
x<
x;
x:
x9
x8
x7
x6
x5
x4
x3
x2
x1
x0
x/
x.
x-
x,
x+
0*
1)
0(
bx1 '
bx0 &
1%
0$
1#
0"
x!
$end
#1
0%
#2
0,
bx01 '
0A
1-
1@
bx10 &
1+
1%
#3
0%
#4
1/
bx101 '
1C
00
0B
bx010 &
0.
1%
#5
0%
#6
02
bx0101 '
0E
13
1D
bx1010 &
11
1%
#7
0%
#8
15
bx10101 '
1G
06
0F
bx01010 &
04
1%
#9
0%
#10
08
bx010101 '
0I
19
1H
bx101010 &
17
1%
#11
0%
#12
1;
bx1010101 '
1K
0<
0J
bx0101010 &
0:
1%
#13
0%
#14
b1010101 '
0M
1L
1!
b10101010 &
1=
1%
#15
0%
#16
1%
#17
0%
#18
1%
#19
0%
#20
1,
0/
12
05
18
0;
1A
0C
1E
0G
1I
0K
b10101011 '
1M
0-
0@
10
1B
03
0D
16
1F
09
0H
1<
1J
0L
0+
1.
01
14
07
1:
b1010100 &
0=
1%
1"
0#
1$
#21
0%
#22
1;
08
15
02
1/
0M
1K
0I
1G
0E
b1010111 '
1C
1L
0<
0J
19
1H
06
0F
13
1D
00
0B
1=
0:
17
04
11
b10101000 &
0.
1%
#23
0%
#24
12
05
18
0;
1E
0G
1I
0K
b10101111 '
1M
03
0D
16
1F
09
0H
1<
1J
0L
01
14
07
1:
b1010000 &
0=
1%
#25
0%
#26
1;
08
15
0M
1K
0I
b1011111 '
1G
1L
0<
0J
19
1H
06
0F
1=
0:
17
b10100000 &
04
1%
#27
0%
#28
18
0;
1I
0K
b10111111 '
1M
09
0H
1<
1J
0L
07
1:
b1000000 &
0=
1%
#29
0%
#30
1;
0M
b1111111 '
1K
1L
0<
0J
1=
b10000000 &
0:
1%
#31
0%
#32
b11111111 '
1M
0L
b0 &
0=
1%
#33
0%
#34
0!
1%
#35
0%
#36
1%
#37
0%
#38
1%
#39
0%
#40
0)
0,
0/
02
05
08
0;
0?
0A
0C
0E
0G
0I
0K
b0 '
0M
1*
1>
1-
1@
10
1B
13
1D
16
1F
19
1H
1<
1J
1L
1(
1+
1.
11
14
17
1:
b11111111 &
1=
1%
0$
#41
0%
#42
1)
b1 '
1?
0*
0>
1!
b11111110 &
0(
1%
1$
#43
0%
#44
1,
b11 '
1A
0-
0@
b11111100 &
0+
1%
#45
0%
#46
1/
b111 '
1C
00
0B
b11111000 &
0.
1%
#47
0%
#48
12
b1111 '
1E
03
0D
b11110000 &
01
1%
#49
0%
#50
15
b11111 '
1G
06
0F
b11100000 &
04
1%
#51
0%
#52
18
b111111 '
1I
09
0H
b11000000 &
07
1%
#53
0%
#54
1;
b1111111 '
1K
0<
0J
b10000000 &
0:
1%
#55
0%
#56
b11111111 '
1M
0L
b0 &
0=
1%
#57
0%
#58
0!
1%
