bin/DFx/inv.v
module inv(
  in,
  out   );
    output reg out;
    input wire in ;

  always @(*)
begin
  out = ~in ;
  end

endmodule

bin/DFx/dfx.v
module FF_scan(
  clk,
  SE,
  SD,
  D,
  Q
  );
    output reg  Q;
    input wire D;
    input wire SE;
    input wire clk;
    input wire SD;

  always @(posedge clk)
    begin
    if (SE== 0 ) 
	   begin
	     Q = D;
	   end
	else
	   begin
	     Q = SD; 
	   end
   end

endmodule

bin/DFx/TBdfx.v
module tester;
reg rSE ;
    reg rSD ;
    reg rD;




wire [7:0] wQ ;
wire [7:0] OutInv ;

reg rclk = 1;
always #1 rclk = !rclk;

  initial begin
     $dumpfile("tester.vcd");
     $dumpvars(0,tester);
     rSE = 0;
     rSD = 1;
     rD = 0;
 
     # 20 rSE= 1;
       rSD= 0;
       rD= 1;
      # 20
       rSE= 0;
       # 2
         rSE= 1;
     # 513 $finish;
  end



  FF_scan FF_scan_intance0(
  .clk(rclk),
  .SE(rSE),
  .SD(rSD),
  .D(rD),
  .Q(wQ[0])
  );

inv intance0(
  .in (wQ[0]),
  .out (OutInv[0]
    )
  );



 FF_scan FF_scan_intance1(
  .clk(rclk),
  .SE(rSE),
  .SD(wQ[0]),
  .D(OutInv[0]),
  .Q(wQ[1])
  );


inv intance1(
  .in(wQ[1]),
  .out(OutInv[1]  )
  );

 FF_scan FF_scan_intance2(
  .clk(rclk),
  .SE(rSE),
  .SD(wQ[1]),
  .D(OutInv[1]),
  .Q(wQ[2])
  );


inv intance2(
  .in(wQ[2]),
  .out(OutInv[2] )
   );


 FF_scan FF_scan_intance3(
  .clk(rclk),
  .SE(rSE),
  .SD(wQ[2]),
  .D(OutInv[2]),
  .Q(wQ[3])
  ); 


inv intance3(
  .in(wQ[3]),
  .out(OutInv[3] )
  );

 FF_scan FF_scan_intance4(
  .clk(rclk),
  .SE(rSE),
  .SD(wQ[3]),
  .D(OutInv[3]),
  .Q(wQ[4])
  );

inv intance4(
  .in(wQ[4]),
  .out(OutInv[4])
  );


 FF_scan FF_scan_intance5(
  .clk(rclk),
  .SE(rSE),
  .SD(wQ[4]),
  .D(OutInv[4]),
  .Q(wQ[5])
  );


inv intance5(
  .in(wQ[5]),
  .out(OutInv[5])
  );


 FF_scan FF_scan_intance6(
  .clk(rclk),
  .SE(rSE),
  .SD(wQ[5]),
  .D(OutInv[5]),
  .Q(wQ[6])
  );


inv intance6(
  .in(wQ[6]),
  .out(OutInv[6])
  );


 FF_scan FF_scan_intance7(
  .clk(rclk),
  .SE(rSE),
  .SD(wQ[6]),
  .D(OutInv[6]),
  .Q(wQ[7])
  );

 inv intance7(
  .in(wQ[7]),
  .out(OutInv[7])
  );
endmodule

bin/DFx/tester.vcd
$date
	Thu Jul 26 00:15:29 2018
$end
$version
	Icarus Verilog
$end
$timescale
	1s
$end
$scope module tester $end
$var wire 8 ! wQ [7:0] $end
$var wire 8 " OutInv [7:0] $end
$var reg 1 # rD $end
$var reg 1 $ rSD $end
$var reg 1 % rSE $end
$var reg 1 & rclk $end
$scope module FF_scan_intance0 $end
$var wire 1 # D $end
$var wire 1 $ SD $end
$var wire 1 % SE $end
$var wire 1 & clk $end
$var reg 1 ' Q $end
$upscope $end
$scope module FF_scan_intance1 $end
$var wire 1 ( D $end
$var wire 1 ) SD $end
$var wire 1 % SE $end
$var wire 1 & clk $end
$var reg 1 * Q $end
$upscope $end
$scope module FF_scan_intance2 $end
$var wire 1 + D $end
$var wire 1 , SD $end
$var wire 1 % SE $end
$var wire 1 & clk $end
$var reg 1 - Q $end
$upscope $end
$scope module FF_scan_intance3 $end
$var wire 1 . D $end
$var wire 1 / SD $end
$var wire 1 % SE $end
$var wire 1 & clk $end
$var reg 1 0 Q $end
$upscope $end
$scope module FF_scan_intance4 $end
$var wire 1 1 D $end
$var wire 1 2 SD $end
$var wire 1 % SE $end
$var wire 1 & clk $end
$var reg 1 3 Q $end
$upscope $end
$scope module FF_scan_intance5 $end
$var wire 1 4 D $end
$var wire 1 5 SD $end
$var wire 1 % SE $end
$var wire 1 & clk $end
$var reg 1 6 Q $end
$upscope $end
$scope module FF_scan_intance6 $end
$var wire 1 7 D $end
$var wire 1 8 SD $end
$var wire 1 % SE $end
$var wire 1 & clk $end
$var reg 1 9 Q $end
$upscope $end
$scope module FF_scan_intance7 $end
$var wire 1 : D $end
$var wire 1 ; SD $end
$var wire 1 % SE $end
$var wire 1 & clk $end
$var reg 1 < Q $end
$upscope $end
$scope module intance0 $end
$var wire 1 = in $end
$var reg 1 > out $end
$upscope $end
$scope module intance1 $end
$var wire 1 ? in $end
$var reg 1 @ out $end
$upscope $end
$scope module intance2 $end
$var wire 1 A in $end
$var reg 1 B out $end
$upscope $end
$scope module intance3 $end
$var wire 1 C in $end
$var reg 1 D out $end
$upscope $end
$scope module intance4 $end
$var wire 1 E in $end
$var reg 1 F out $end
$upscope $end
$scope module intance5 $end
$var wire 1 G in $end
$var reg 1 H out $end
$upscope $end
$scope module intance6 $end
$var wire 1 I in $end
$var reg 1 J out $end
$upscope $end
$scope module intance7 $end
$var wire 1 K in $end
$var reg 1 L out $end
$upscope $end
$upscope $end
$enddefinitions $end
#0
$dumpvars
xL
xK
xJ
xI
xH
xG
xF
xE
xD
xC
xB
xA
x@
x?
1>
0=
x<
x;
x:
x9
x8
x7
x6
x5
x4
x3
x2
x1
x0
x/
x.
x-
x,
x+
x*
0)
1(
0'
1&
0%
1$
0#
bx1 "
bx0 !
$end
#1
0&
#2
0+
bx01 "
0@
1,
1?
bx10 !
1*
1&
#3
0&
#4
1.
bx101 "
1B
0/
0A
bx010 !
0-
1&
#5
0&
#6
01
bx0101 "
0D
12
1C
bx1010 !
10
1&
#7
0&
#8
14
bx10101 "
1F
05
0E
bx01010 !
03
1&
#9
0&
#10
07
bx010101 "
0H
18
1G
bx101010 !
16
1&
#11
0&
#12
1:
bx1010101 "
1J
0;
0I
bx0101010 !
09
1&
#13
0&
#14
b1010101 "
0L
1K
b10101010 !
1<
1&
#15
0&
#16
1&
#17
0&
#18
1&
#19
0&
#20
1+
0.
11
04
17
0:
1@
0B
1D
0F
1H
0J
b10101011 "
1L
0,
0?
1/
1A
02
0C
15
1E
08
0G
1;
1I
0K
0*
1-
00
13
06
19
b1010100 !
0<
1&
1#
0$
1%
#21
0&
#22
1:
07
14
01
1.
0L
1J
0H
1F
0D
b1010111 "
1B
1K
0;
0I
18
1G
05
0E
12
1C
0/
0A
1<
09
16
03
10
b10101000 !
0-
1&
#23
0&
#24
11
04
17
0:
1D
0F
1H
0J
b10101111 "
1L
02
0C
15
1E
08
0G
1;
1I
0K
00
13
06
19
b1010000 !
0<
1&
#25
0&
#26
1:
07
14
0L
1J
0H
b1011111 "
1F
1K
0;
0I
18
1G
05
0E
1<
09
16
b10100000 !
03
1&
#27
0&
#28
17
0:
1H
0J
b10111111 "
1L
08
0G
1;
1I
0K
06
19
b1000000 !
0<
1&
#29
0&
#30
1:
0L
b1111111 "
1J
1K
0;
0I
1<
b10000000 !
09
1&
#31
0&
#32
b11111111 "
1L
0K
b0 !
0<
1&
#33
0&
#34
1&
#35
0&
#36
1&
#37
0&
#38
1&
#39
0&
#40
0(
0+
0.
01
04
07
0:
0>
0@
0B
0D
0F
0H
0J
b0 "
0L
1)
1=
1,
1?
1/
1A
12
1C
15
1E
18
1G
1;
1I
1K
1'
1*
1-
10
13
16
19
b11111111 !
1<
1&
0%
#41
0&
#42
1(
b1 "
1>
0)
0=
b11111110 !
0'
1&
1%
#43
0&
#44
1+
b11 "
1@
0,
0?
b11111100 !
0*
1&
#45
0&
#46
1.
b111 "
1B
0/
0A
b11111000 !
0-
1&
#47
0&
#48
11
b1111 "
1D
02
0C
b11110000 !
00
1&
#49
0&
#50
14
b11111 "
1F
05
0E
b11100000 !
03
1&
#51
0&
#52
17
b111111 "
1H
08
0G
b11000000 !
06
1&
#53
0&
#54
1:
b1111111 "
1J
0;
0I
b10000000 !
09
1&
#55
0&
#56
b11111111 "
1L
0K
b0 !
0<
1&
